Metadata-Version: 1.0
Name: ngdistributionsudacity
Version: 0.1
Summary: Gaussian distributions and Binomial distributions
Home-page: UNKNOWN
Author: Idriss Nguepi
Author-email: inguepi@aimsammi.org
License: UNKNOWN
Platform: UNKNOWN
